say_hello/__init__.py
say_hello/say_hello.py
xgh_say_hello-0.0.2.dist-info/METADATA
xgh_say_hello-0.0.2.dist-info/WHEEL
xgh_say_hello-0.0.2.dist-info/entry_points.txt
xgh_say_hello-0.0.2.dist-info/top_level.txt
xgh_say_hello-0.0.2.dist-info/RECORD
