Metadata-Version: 2.1
Name: xgh-say-hello
Version: 0.0.2
Summary: Just for learning publish a python package
Home-page: UNKNOWN
Author: xgh
License: UNKNOWN
Platform: UNKNOWN
